bbanalysis/MLB_2018_2025_Cleaned.csv
bbanalysis/MLB_2018_2025_Full.csv
bbanalysis/__init__.py
bbanalysis/analysis.py
bbanalysis/cleaning.py
bbanalysis/gathering_salaries.py
bbanalysis/gathering_stats.py
bbanalysis/plots/age_at_contract.png
bbanalysis/plots/comprehensive_analysis.png
bbanalysis/plots/contract_boxplots.png
bbanalysis/plots/contract_trajectory.png
bbanalysis/salaries.csv
bbanalysis/salaries.json
bbanalysis/streamlit_app.py
bbanalysis/unique_links.json
bbanalysis-0.2.2.dist-info/WHEEL
bbanalysis-0.2.2.dist-info/METADATA
bbanalysis-0.2.2.dist-info/RECORD
